{
	"$schema": "https://schema.management.azure.com/schemas/2015-01-01/deploymentParameters.json#",
	"contentVersion": "1.0.0.0",
	"parameters": {
		"factoryName": {
			"value": "adf-supplychain234"
		},
		"AzureDataLakeStorage1_accountKey": {
			"value": ""
		},
		"AzureSqlDatabase1_connectionString": {
			"value": ""
		},
		"eduellipse_accountKey": {
			"value": ""
		},
		"AzureDataLakeStorage1_properties_typeProperties_url": {
			"value": "https://datalakegen2lynn.dfs.core.windows.net/"
		},
		"eduellipse_properties_typeProperties_url": {
			"value": "https://gen2eduellipse.dfs.core.windows.net/"
		},
		"containerUri": {
			"value": ""
		},
		"containerSasToken": {
			"value": ""
		}
	}
}